easytrain/__init__.py
easytrain/base.py
easytrain/callbacks.py
easytrain/classifier.py
easytrain/data.py
easytrain/loss.py
easytrain/metrics.py
easytrain-0.0.5.dist-info/LICENSE
easytrain-0.0.5.dist-info/METADATA
easytrain-0.0.5.dist-info/WHEEL
easytrain-0.0.5.dist-info/top_level.txt
easytrain-0.0.5.dist-info/RECORD
