Metadata-Version: 2.1
Name: easytrain
Version: 0.0.5
Summary: a train tool
Home-page: https://gitee.com/aierwiki/easytrain
Author: Tang Yubin
Author-email: tang-yu-bin@qq.com
Classifier: Programming Language :: Python :: 3
Classifier: License :: OSI Approved :: MIT License
Classifier: Operating System :: OS Independent
License-File: LICENSE
